README.rst
setup.py
django_dict_response/__init__.py
django_dict_response/middlewares.py
django_dict_response.egg-info/PKG-INFO
django_dict_response.egg-info/SOURCES.txt
django_dict_response.egg-info/dependency_links.txt
django_dict_response.egg-info/pbr.json
django_dict_response.egg-info/requires.txt
django_dict_response.egg-info/top_level.txt